kiran/__init__.py
kiran/_about.py
kiran/cli.py
kiran/errors.py
kiran/impl.py
kiran/logger.py
kiran/abc/base.py
kiran/abc/chats.py
kiran/abc/enums.py
kiran/abc/message.py
kiran/abc/subtype.py
kiran/abc/user.py
kiran/core/methods.py
kiran/tabc/base.py
kiran/tabc/chat.py
kiran/tabc/message.py
kiran/tabc/resource.py
kiran/tabc/user.py
kiran-0.0.1.dev0.dist-info/METADATA
kiran-0.0.1.dev0.dist-info/WHEEL
kiran-0.0.1.dev0.dist-info/entry_points.txt
kiran-0.0.1.dev0.dist-info/top_level.txt
kiran-0.0.1.dev0.dist-info/RECORD
